chai/__init__.py
chai/cli.py
chai/persistence.py
chai/spinner.py
chai/base/__init__.py
chai/base/chat.py
chai/base/message.py
chai/base/provider.py
chai/providers/__init__.py
chai/providers/anthropic.py
chai/providers/google.py
chai/providers/mistral.py
chai/providers/openai.py
chai/providers/providers.py
chai/providers/xai.py
chai_chat-1.0.1.dist-info/METADATA
chai_chat-1.0.1.dist-info/WHEEL
chai_chat-1.0.1.dist-info/entry_points.txt
chai_chat-1.0.1.dist-info/top_level.txt
chai_chat-1.0.1.dist-info/RECORD
