Metadata-Version: 2.2
Name: chai-chat
Version: 1.0.1
Summary: Chat with AI in the terminal
Author-email: Darik Harter <darik.harter@gmail.com>
Maintainer-email: Darik Harter <darik.harter@gmail.com>
Project-URL: Homepage, https://github.com/itsdarik/chai
Project-URL: Repository, https://github.com/itsdarik/chai
Project-URL: Issues, https://github.com/itsdarik/chai/issues
Project-URL: Changelog, https://github.com/itsdarik/chai/releases
Keywords: ai,anthropic,chai,chat,chatgpt,claude,cli,codestral,gemini,genai,google,gpt,grok,le chat,llm,mistral,ollama,openai,terminal,xai
Classifier: Development Status :: 5 - Production/Stable
Classifier: Environment :: Console
Classifier: Intended Audience :: Developers
Classifier: Intended Audience :: End Users/Desktop
Classifier: License :: OSI Approved :: Apache Software License
Classifier: Natural Language :: English
Classifier: Operating System :: OS Independent
Classifier: Programming Language :: Python :: 3.13
Classifier: Topic :: Communications :: Chat
Classifier: Topic :: Scientific/Engineering :: Artificial Intelligence
Classifier: Topic :: Terminals
Classifier: Topic :: Text Processing :: Linguistic
Classifier: Typing :: Typed
Requires-Python: >=3.13.2
Requires-Dist: anthropic>=0.49.0
Requires-Dist: google-genai>=1.5.0
Requires-Dist: mistralai>=1.5.1
Requires-Dist: openai>=1.66.3
Requires-Dist: rich>=13.9.4
